golay/__init__.py
golay/golay.py
golay-1.0.dist-info/LICENSE
golay-1.0.dist-info/METADATA
golay-1.0.dist-info/WHEEL
golay-1.0.dist-info/top_level.txt
golay-1.0.dist-info/RECORD
